apexllm/__init__.py
apexllm/core.py
apexllm-0.0.2.dist-info/licenses/LICENSE
apexllm-0.0.2.dist-info/METADATA
apexllm-0.0.2.dist-info/WHEEL
apexllm-0.0.2.dist-info/top_level.txt
apexllm-0.0.2.dist-info/RECORD
