Metadata-Version: 2.4
Name: apexllm
Version: 0.0.2
Summary: A lightweight and efficient LLM utility package.
Author-email: Apex Developer <apex@example.com>
License-Expression: MIT
Project-URL: Homepage, https://github.com/apex-dev/apexllm
Project-URL: Bug Tracker, https://github.com/apex-dev/apexllm/issues
Project-URL: Repository, https://github.com/apex-dev/apexllm
Classifier: Programming Language :: Python :: 3
Classifier: Operating System :: OS Independent
Classifier: Development Status :: 3 - Alpha
Classifier: Intended Audience :: Developers
Classifier: Topic :: Software Development :: Libraries :: Python Modules
Requires-Python: >=3.8
License-File: LICENSE
Requires-Dist: openai>=1.0.0
Requires-Dist: requests>=2.25.0
Requires-Dist: tiktoken>=0.5.0
Requires-Dist: python-dotenv>=1.0.0
Dynamic: license-file
